{"master": [{"commit_oid": "fdb453f94b8d5bd566f39554a56ccee17aaefb94", "commit_date": "2018-07-28T19:21:52Z", "commit_message": "Merge pull request #35 from mjtrangoni/fix-gometalinter\n\nFix build issue #34", "commit_author": "", "message_analysis": {"glm6b_2": [], "manual": [], "noob_engine": []}}, {"commit_oid": "232e30cf3a8e63957c5e054e478acfb8a7f632ea", "commit_date": "2018-07-28T16:22:51Z", "commit_message": "Add Atoi error handling to fix gosec warning.\n\nSee,\n\n$ make gometalinter\n>> linting code\ngluster_client.go:151::warning: Errors unhandled.,LOW,HIGH (gosec)\ngluster_client.go:151::warning: Errors unhandled.,LOW,HIGH (gosec)\ngluster_client.go:151::warning: Errors unhandled.,LOW,HIGH (gosec)\nmake: *** [Makefile:59: gometalinter] Error 1", "commit_author": "", "message_analysis": {"glm6b_2": [], "manual": [], "noob_engine": []}}, {"commit_oid": "58a529efa18fdb4178f2492aa1f9a6eb29c88366", "commit_date": "2018-07-28T16:11:17Z", "commit_message": "Move gometalinter configuration to a .gometalinter.json file\n\nI did some other changes here too,\n\n* Re-Enabling the gas check.\n* Acknowledge Subprocess with variables, and subprocess audit.\n  See, https://github.com/securego/gosec/issues/204", "commit_author": "", "message_analysis": {"glm6b_2": [], "manual": [], "noob_engine": []}}, {"commit_oid": "b2918c08984173e9f95b4682b8759a2bcf88882c", "commit_date": "2018-07-27T17:41:14Z", "commit_message": "Update dep config format, and do some vendoring updates", "commit_author": "", "message_analysis": {"glm6b_2": [], "manual": [], "noob_engine": []}}, {"commit_oid": "4d37e4c9c45e0e11f5155638e5c56c0ae3c2937a", "commit_date": "2018-07-25T13:33:15Z", "commit_message": "Merge pull request #33 from mjtrangoni/fix-codespell-issues\n\nFix codespell issues", "commit_author": "", "message_analysis": {"glm6b_2": [], "manual": [], "noob_engine": []}}, {"commit_oid": "d2197221e1ec17204465c4a6ca27a3e72974d1f2", "commit_date": "2018-07-10T17:49:38Z", "commit_message": "Add Codespell check to CircleCI", "commit_author": "", "message_analysis": {"glm6b_2": [], "manual": [], "noob_engine": []}}, {"commit_oid": "9dcb449efbff1b522e364ceb5408bfdf6ea88cf4", "commit_date": "2018-07-10T17:46:42Z", "commit_message": "Add go 1.10.x to TravisCI", "commit_author": "", "message_analysis": {"glm6b_2": [], "manual": [], "noob_engine": []}}, {"commit_oid": "ec680e4a5b949f3686864b7ab5a0a6e48eb2ad3d", "commit_date": "2018-07-10T17:45:28Z", "commit_message": "Add codespell fixes\n\nSee,\n$ codespell -S \"*./vendor*,*.git*\"\n./README.md:40: copys  ==> copies\n./README.md:40: builded  ==> built\n./README.md:95: Descritpion  ==> Description\n./gluster_client.go:157: processess  ==> processes\n./structs/xmlStructs_test.go:86: does't  ==> doesn't\n./structs/xmlStructs_test.go:223: Excpected  ==> Expected\n./structs/xmlStructs.go:11: repesents  ==> represents\n./structs/xmlStructs.go:53: repesents  ==> represents\n./structs/xmlStructs.go:99: repesents  ==> represents\n./structs/xmlStructs.go:164: repesents  ==> represents\n./structs/xmlStructs.go:313: fuction  ==> function", "commit_author": "", "message_analysis": {"glm6b_2": [], "manual": [], "noob_engine": []}}, {"commit_oid": "dbfcaa40fb8739f2d10144a339ae256b9c7b338c", "commit_date": "2018-07-10T08:43:49Z", "commit_message": "Merge pull request #29 from mjtrangoni/fix-promtool-issues\n\nFix `promtool check metrics` issues", "commit_author": "", "message_analysis": {"glm6b_2": [], "manual": [], "noob_engine": []}}, {"commit_oid": "5a90738ad1f0a0ed4ebb02f582649b7c45a2f38a", "commit_date": "2018-01-11T20:57:20Z", "commit_message": "Fix `brick_data` and `brick_duration` metrics", "commit_author": "", "message_analysis": {"glm6b_2": [], "manual": [], "noob_engine": []}}, {"commit_oid": "7905efc1fb94fdb22e1473ba31951c59823f8ad1", "commit_date": "2018-01-11T19:04:49Z", "commit_message": "Remove deprecated `gluster volume list` reference", "commit_author": "", "message_analysis": {"glm6b_2": [], "manual": [], "noob_engine": []}}, {"commit_oid": "58dd2437a10f4bcb17c520781a9ee3a67a97f715", "commit_date": "2018-01-11T19:03:09Z", "commit_message": "Fix gluster_volumes_count metric name", "commit_author": "", "message_analysis": {"glm6b_2": [], "manual": [], "noob_engine": []}}, {"commit_oid": "1cf1e0e7e9b24d835ae2b029cb70caf6249c2b9f", "commit_date": "2018-01-11T18:53:22Z", "commit_message": "Fix gluster_brick_count metric name", "commit_author": "", "message_analysis": {"glm6b_2": [], "manual": [], "noob_engine": []}}, {"commit_oid": "6e44c56e02d37471ebea0b443bf8c04724de9745", "commit_date": "2018-01-11T18:33:52Z", "commit_message": "Fix Fop.Name README.md information", "commit_author": "", "message_analysis": {"glm6b_2": [], "manual": [], "noob_engine": []}}, {"commit_oid": "074223e1c8442bfe49b9e40d734dd2ff479ba2da", "commit_date": "2018-01-11T18:21:16Z", "commit_message": "Fix file operations promtool issues", "commit_author": "", "message_analysis": {"glm6b_2": [], "manual": [], "noob_engine": []}}, {"commit_oid": "5f3221120ee651c94b7baf5f21f515a4d7ed3225", "commit_date": "2018-01-11T18:20:48Z", "commit_message": "Add inodes metrics to README.md", "commit_author": "", "message_analysis": {"glm6b_2": [], "manual": [], "noob_engine": []}}, {"commit_oid": "a0189913fd10f6b12c3b631ce2a81fb119bd488f", "commit_date": "2018-01-11T14:10:10Z", "commit_message": "Merge pull request #28 from mjtrangoni/add-inode-metrics\n\nAdd inode metrics", "commit_author": "", "message_analysis": {"glm6b_2": [], "manual": [], "noob_engine": []}}, {"commit_oid": "97765c8f8fc43c4f69f17c3fcd990dfd030a4837", "commit_date": "2018-01-08T21:54:28Z", "commit_message": "Add volume inodes metrics", "commit_author": "", "message_analysis": {"glm6b_2": [], "manual": [], "noob_engine": []}}, {"commit_oid": "ce04fbc5aaa0c1da920b223db93ed361b020def8", "commit_date": "2018-01-08T19:02:55Z", "commit_message": "gluster_client.go: remove unnecessary append", "commit_author": "", "message_analysis": {"glm6b_2": [], "manual": [], "noob_engine": []}}, {"commit_oid": "6685200b992fe46dd286a5d45497cd9945b643ef", "commit_date": "2018-01-08T11:08:28Z", "commit_message": "Merge pull request #26 from mjtrangoni/gluster-update\n\nUpdate to Debian 9 (stretch) and GlusterFS v3.12", "commit_author": "", "message_analysis": {"glm6b_2": [], "manual": [], "noob_engine": []}}, {"commit_oid": "0c720b824e11a8c6c0d72a8979470487f171860e", "commit_date": "2018-01-07T20:39:42Z", "commit_message": "Update to Debian 9 (stretch) and GlusterFS v3.12", "commit_author": "", "message_analysis": {"glm6b_2": [], "manual": [], "noob_engine": []}}, {"commit_oid": "a49c878ee56618d743261dbf9e83601ef149d838", "commit_date": "2018-01-06T18:07:46Z", "commit_message": "Merge pull request #24 from mjtrangoni/build\n\nProject build tools update", "commit_author": "", "message_analysis": {"glm6b_2": [], "manual": [], "noob_engine": []}}, {"commit_oid": "d26d585ff79a98122886d6047376031536bc01c0", "commit_date": "2018-01-06T17:07:24Z", "commit_message": "Remove example config\n\nWith the documentation link it is not necessary to provide the examples", "commit_author": "", "message_analysis": {"glm6b_2": [], "manual": [], "noob_engine": []}}, {"commit_oid": "1a27bf422047d3e36142a89952afb3eba262c6f4", "commit_date": "2018-01-06T16:52:03Z", "commit_message": "Switch to kingpin command line parser", "commit_author": "", "message_analysis": {"glm6b_2": [], "manual": [], "noob_engine": []}}, {"commit_oid": "49c4242b5598dd892f9eac732fa6494c1eea488b", "commit_date": "2018-01-06T16:52:03Z", "commit_message": "Travis: Update to go1.9.x and fix some issues", "commit_author": "", "message_analysis": {"glm6b_2": [], "manual": [], "noob_engine": []}}, {"commit_oid": "5bc9465d2ef588b8754605405fb5d3cb107e06f8", "commit_date": "2018-01-06T14:44:41Z", "commit_message": "Add xml.Unmarshal error check and fix errcheck issues", "commit_author": "", "message_analysis": {"glm6b_2": [], "manual": [], "noob_engine": []}}, {"commit_oid": "78b8256adc4397bb47f426c58438df458d1a1929", "commit_date": "2018-01-06T14:44:41Z", "commit_message": "Update README.md Makefile target references", "commit_author": "", "message_analysis": {"glm6b_2": [], "manual": [], "noob_engine": []}}, {"commit_oid": "450660b42f63c7ac3c815df5616634a234c5221b", "commit_date": "2018-01-06T14:44:41Z", "commit_message": "Makefile: Exclude some gometalinter checks", "commit_author": "", "message_analysis": {"glm6b_2": [], "manual": [], "noob_engine": []}}, {"commit_oid": "eb0f64337a7f30ac51af2eee6327a7350965794f", "commit_date": "2018-01-06T14:44:41Z", "commit_message": "Fix interfacer suggestions", "commit_author": "", "message_analysis": {"glm6b_2": [], "manual": [], "noob_engine": []}}, {"commit_oid": "dfd6c8d3e2b57fa22da64f93be4aa20d50a7e737", "commit_date": "2018-01-06T14:44:41Z", "commit_message": "Fix megacheck issues", "commit_author": "", "message_analysis": {"glm6b_2": [], "manual": [], "noob_engine": []}}, {"commit_oid": "a7454a90980469732ed735de02edcffdc528ffa6", "commit_date": "2018-01-06T14:44:41Z", "commit_message": "Fix golint issues", "commit_author": "", "message_analysis": {"glm6b_2": [], "manual": [], "noob_engine": []}}, {"commit_oid": "6c7c37337eaf8e8b391122fc1a666430c9b4329b", "commit_date": "2018-01-06T14:44:41Z", "commit_message": "Fix unnecessary conversion issues", "commit_author": "", "message_analysis": {"glm6b_2": [], "manual": [], "noob_engine": []}}, {"commit_oid": "5c6e944b31c5fb4b651ebb8ffb9a49d10c29b868", "commit_date": "2018-01-06T14:44:41Z", "commit_message": "Makefile: add clean, vet, depcheck, and gometalinter targets.", "commit_author": "", "message_analysis": {"glm6b_2": [], "manual": [], "noob_engine": []}}, {"commit_oid": "a1ab25672a6ffd5011e41549c867dea5c80c018c", "commit_date": "2018-01-06T11:16:01Z", "commit_message": "Fix format by go fmt", "commit_author": "", "message_analysis": {"glm6b_2": [], "manual": [], "noob_engine": []}}, {"commit_oid": "95da889b33d3440513710d8ba800453761314438", "commit_date": "2018-01-06T11:00:55Z", "commit_message": "Add CHANGELOG.md file", "commit_author": "", "message_analysis": {"glm6b_2": [], "manual": [], "noob_engine": []}}, {"commit_oid": "4f6bbdb16fe01dcd21aa905da5a2e7daac2f318a", "commit_date": "2018-01-06T11:00:11Z", "commit_message": "Remove deprecated go build", "commit_author": "", "message_analysis": {"glm6b_2": [], "manual": [], "noob_engine": []}}, {"commit_oid": "10a03d875f5bde9b1abe536be6b95879ae11abc8", "commit_date": "2018-01-06T10:32:36Z", "commit_message": "Fix promu build information", "commit_author": "", "message_analysis": {"glm6b_2": [], "manual": [], "noob_engine": []}}, {"commit_oid": "442ba9b19e6c0b0fe80b8bbd5b7bdab1b8cd6bb2", "commit_date": "2018-01-06T10:18:24Z", "commit_message": "Switch from govendor to dep", "commit_author": "", "message_analysis": {"glm6b_2": [], "manual": [], "noob_engine": []}}, {"commit_oid": "4246cba34c4f32322157755d9b124e95fd29482d", "commit_date": "2018-01-03T18:15:16Z", "commit_message": "Updated contributors", "commit_author": "", "message_analysis": {"glm6b_2": [], "manual": [], "noob_engine": []}}, {"commit_oid": "195a0d471d38adab5ab1a1a15cb0414201b119da", "commit_date": "2017-11-21T14:50:14Z", "commit_message": "Update README.md", "commit_author": "", "message_analysis": {"glm6b_2": [], "manual": [], "noob_engine": []}}, {"commit_oid": "868da4d249d2d40cb94f5a35c38cd1f4b127ac47", "commit_date": "2017-09-26T13:27:16Z", "commit_message": "Help needed\n\nthis exporter is not actively developed any more", "commit_author": "", "message_analysis": {"glm6b_2": [], "manual": [], "noob_engine": []}}, {"commit_oid": "9b32cbe00c449a4d51d685efce471072b9c2c78f", "commit_date": "2017-05-09T09:25:39Z", "commit_message": "increases version", "commit_author": "", "message_analysis": {"glm6b_2": [], "manual": [], "noob_engine": []}}]}