{"master": [{"commit_oid": "be51b94b083bad6fa0716ad6dc97d12f4462f8d4", "commit_date": "2023-07-10T09:32:31Z", "commit_message": "Merge pull request #119 from poncovka/master-externally_managed_debian\n\nCI: Don't use the externally managed environment on Debian", "commit_author": "", "message_analysis": {"glm6b_2": [], "llama2_7b_chat": [], "manual": [], "noob_engine": []}}, {"commit_oid": "5edaa25eac3c66b33e7766b3a78702db82c37f47", "commit_date": "2023-06-23T10:31:23Z", "commit_message": "CI: Don't use the externally managed environment on Debian\n\nUse the fix from the commit ec1ae5b1bbb1fb46e8d461c266311219b010a98e.", "commit_author": "", "message_analysis": {"glm6b_2": [], "llama2_7b_chat": [], "manual": [], "noob_engine": []}}, {"commit_oid": "86a058263037f8ae03a544b164eede29635e3078", "commit_date": "2023-05-31T13:51:49Z", "commit_message": "Merge pull request #117 from poncovka/master-fix_failing_tests\n\nCI: Fix the failing tests", "commit_author": "", "message_analysis": {"glm6b_2": [], "llama2_7b_chat": [], "manual": [], "noob_engine": []}}, {"commit_oid": "ec1ae5b1bbb1fb46e8d461c266311219b010a98e", "commit_date": "2023-05-28T16:37:05Z", "commit_message": "CI: Don't use the externally managed environment on Ubuntu\n\nBased on https://peps.python.org/pep-0668/, operating systems can now mark their\nPython environments as \"externally managed. Because of that, Ubuntu tests are now\nfailing with the \"This environment is externally managed\" error. Create a virtual\nenvironment and use it instead to fix the tests.", "commit_author": "", "message_analysis": {"glm6b_2": [], "llama2_7b_chat": [], "manual": [], "noob_engine": []}}, {"commit_oid": "a68fd442f185ea546f185651e4e4f05708a68e8d", "commit_date": "2023-05-26T13:23:17Z", "commit_message": "CI: Fix locale settings in testing containers\n\nDocumentation builds started to fail with the `unsupported locale setting` error\nsince Sphinx removed its workaround for `locale.setlocale(locale.LC_ALL, '')`.\n\nBased on https://peps.python.org/pep-0538/, Linux containers should set only\n`LC_CTYPE=C.UTF-8` to get a consistent behaviour across all distributions.", "commit_author": "", "message_analysis": {"glm6b_2": [], "llama2_7b_chat": [], "manual": [], "noob_engine": []}}, {"commit_oid": "d8cddb57a9d5e19202d156e24fd3387479091664", "commit_date": "2023-05-26T13:23:10Z", "commit_message": "CI: Fix the Pylint warnings about the overgeneral-exceptions option\n\nSpecifying exception names in the overgeneral-exceptions option without module\nname is deprecated and support for it will be removed in pylint 3.0. Use fully\nqualified name (maybe 'builtins.Exception' ?) instead.", "commit_author": "", "message_analysis": {"glm6b_2": [], "llama2_7b_chat": [], "manual": [], "noob_engine": []}}, {"commit_oid": "64b6b4d9e37cd7e0cbf4a7bf75faa7cdbd01086d", "commit_date": "2022-11-10T15:51:34Z", "commit_message": "Merge pull request #111 from poncovka/master-src\n\nMove the source files to /src", "commit_author": "", "message_analysis": {"glm6b_2": [], "llama2_7b_chat": [], "manual": [], "noob_engine": []}}, {"commit_oid": "8b626dd721d4fdb0a2636084c1121d22b2766f5a", "commit_date": "2022-11-09T15:30:42Z", "commit_message": "CI: Run tests on the installed package in Travis\n\n* Run `make install` to build and install the `dasbus` package.\n* Run `make test-install` to test the installed `dasbus` package.", "commit_author": "", "message_analysis": {"glm6b_2": [], "llama2_7b_chat": [], "manual": [], "noob_engine": []}}, {"commit_oid": "95abffbbf2ef7a120ee128b0d5dcaa4c425e4469", "commit_date": "2022-11-09T15:30:42Z", "commit_message": "CI: Use pytest instead of unittest\n\n* Run the unit tests with pytest instead of unittest.\n* Keep the pytest configuration in the pyproject.toml file.", "commit_author": "", "message_analysis": {"glm6b_2": [], "llama2_7b_chat": [], "manual": [], "noob_engine": []}}, {"commit_oid": "627f06aef7579fe7f75cebdac9f1c1bb7be320df", "commit_date": "2022-11-09T15:30:42Z", "commit_message": "CI: Remove the .coveragerc file\n\nMove the configuration to the pyproject.toml file.", "commit_author": "", "message_analysis": {"glm6b_2": [], "llama2_7b_chat": [], "manual": [], "noob_engine": []}}, {"commit_oid": "11cb50044727e6e5d5b82eea8b749f6ad9a39fda", "commit_date": "2022-11-09T15:28:43Z", "commit_message": "CI: Add the pyproject.toml file\n\n* Keep info about the Python package in the pyproject.toml file.\n* Run `python -m build` to build the distribution archive.\n* Fix building on Debian and Ubuntu by installing python3-venv.\n* Follow the latest Python packaging guidelines in the .spec file.\n* Remove setup.py.", "commit_author": "", "message_analysis": {"glm6b_2": [], "llama2_7b_chat": [], "manual": [], "noob_engine": []}}, {"commit_oid": "0fe67335a2624a4ca2cc29fc80af274b84afa722", "commit_date": "2022-11-09T08:44:35Z", "commit_message": "Move the source files to /src\n\nMove the source files of the dasbus package to the /src directory, so\nwe can easily run tests on the source files and on the installed files.", "commit_author": "", "message_analysis": {"glm6b_2": [], "llama2_7b_chat": [], "manual": [], "noob_engine": []}}, {"commit_oid": "2434b55db02a4f43132ff20182db1672ab4ec7d0", "commit_date": "2022-11-09T08:43:55Z", "commit_message": "Merge pull request #113 from poncovka/master-requirements\n\nCI: Add the requirements.txt file", "commit_author": "", "message_analysis": {"glm6b_2": [], "llama2_7b_chat": [], "manual": [], "noob_engine": []}}, {"commit_oid": "0328aca770a72ab8decc1fbed1147ed7ae93bb23", "commit_date": "2022-11-08T16:47:26Z", "commit_message": "CI: Add the requirements.txt file\n\nKeep build and test pip requirements in the requirements.txt file.", "commit_author": "", "message_analysis": {"glm6b_2": [], "llama2_7b_chat": [], "manual": [], "noob_engine": []}}, {"commit_oid": "01589bdd26fb4e04913081a6ead938bb27031965", "commit_date": "2022-11-08T13:21:56Z", "commit_message": "Merge pull request #112 from poncovka/master-packit_clean_up\n\nCI: Update the .packit.yaml file", "commit_author": "", "message_analysis": {"glm6b_2": [], "llama2_7b_chat": [], "manual": [], "noob_engine": []}}, {"commit_oid": "8a401341887d79057d463ce3516edc87cf7809f3", "commit_date": "2022-11-08T13:21:37Z", "commit_message": "Merge pull request #110 from poncovka/master-generate_api_doc\n\nAutomatically generate the API reference", "commit_author": "", "message_analysis": {"glm6b_2": [], "llama2_7b_chat": [], "manual": [], "noob_engine": []}}, {"commit_oid": "752bb66f3cd6f08477313b062f8ae852defe0608", "commit_date": "2022-11-08T10:36:43Z", "commit_message": "CI: Update the .packit.yaml file\n\n* Resolve warnings from `packit validate-config`.\n* Use `upstream_tag_template` to get the current version.\n* Enable Packit tests on pull requests.\n* Run pull request jobs only for Fedora Rawhide.\n* Disable Copr builds for Anaconda-devel.", "commit_author": "", "message_analysis": {"glm6b_2": [], "llama2_7b_chat": [], "manual": [], "noob_engine": []}}]}